SegmentationUpsampler/Extractor.py
SegmentationUpsampler/FillGaps.py
SegmentationUpsampler/FillGapsNumba.py
SegmentationUpsampler/ImageBase.py
SegmentationUpsampler/LabelSeparater.py
SegmentationUpsampler/Preprocess.py
SegmentationUpsampler/UpsampleMultiLabels.py
SegmentationUpsampler/Voxelizer.py
SegmentationUpsampler/VoxelizerNumba.py
SegmentationUpsampler/__init__.py
examples/UpsamplerTest.py
examples/runPythonFunction.py
pysegupsampler-0.0.7.dist-info/licenses/LICENSE
pysegupsampler-0.0.7.dist-info/METADATA
pysegupsampler-0.0.7.dist-info/WHEEL
pysegupsampler-0.0.7.dist-info/top_level.txt
pysegupsampler-0.0.7.dist-info/RECORD
