Metadata-Version: 2.4
Name: pySegUpsampler
Version: 0.0.7
Summary: A python package that upsample segmentated medical image
Author-email: Liangpu Liu <zcemll0@ucl.ac.uk>, Rui Xu <rui.xu@ucl.ac.uk>
Project-URL: Homepage, https://github.com/Donny-bla/segmentation-upsampler/tree/main
Classifier: Programming Language :: Python :: 3
Classifier: License :: OSI Approved :: GNU General Public License v3 (GPLv3)
Classifier: Operating System :: OS Independent
Requires-Python: >=3.9
License-File: LICENSE
Requires-Dist: numpy>=1.26.3
Requires-Dist: scipy>=1.12.0
Requires-Dist: vtk>=9.3.0
Requires-Dist: numba>=0.59.1
Dynamic: license-file
